rlbot_action_client/__init__.py
rlbot_action_client/api_client.py
rlbot_action_client/configuration.py
rlbot_action_client/rest.py
rlbot_action_client/api/__init__.py
rlbot_action_client/api/action_api.py
rlbot_action_client/models/__init__.py
rlbot_action_client/models/action_choice.py
rlbot_action_client/models/api_response.py
rlbot_action_client/models/available_actions.py
rlbot_action_client/models/bot_action.py
rlbot_action_client/models/strategic_category.py
test/__init__.py
test/test_action_api.py
test/test_action_choice.py
test/test_api_response.py
test/test_available_actions.py
test/test_bot_action.py
test/test_strategic_category.py
rlbot_action_client-1.1.0.dist-info/METADATA
rlbot_action_client-1.1.0.dist-info/WHEEL
rlbot_action_client-1.1.0.dist-info/top_level.txt
rlbot_action_client-1.1.0.dist-info/RECORD
