Metadata-Version: 2.1
Name: rlbot-action-client
Version: 1.1.0
Summary: Bot Action Server
Home-page: UNKNOWN
Author: UNKNOWN
Author-email: rlbotofficial@gmail.com
License: UNKNOWN
Keywords: Swagger,Bot Action Server
Platform: UNKNOWN
Requires-Dist: urllib3 (>=1.15)
Requires-Dist: six (>=1.10)
Requires-Dist: certifi
Requires-Dist: python-dateutil
